LICENSE
README.md
django_upman/__init__.py
django_upman/forms.py
django_upman/models.py
django_upman/urls.py
django_upman/views.py
django_upman-0.1.1.dist-info/DESCRIPTION.rst
django_upman-0.1.1.dist-info/METADATA
django_upman-0.1.1.dist-info/metadata.json
django_upman-0.1.1.dist-info/pbr.json
django_upman-0.1.1.dist-info/RECORD
django_upman-0.1.1.dist-info/top_level.txt
django_upman-0.1.1.dist-info/WHEEL
