Metadata-Version: 2.0
Name: django-upman
Version: 0.1.1
Summary: Django uploads manager
Home-page: https://github.com/ipartola/django-upman
Author: Igor Partola
Author-email: igor@igorpartola.com
License: MIT License
Keywords: Django uploads manager
Platform: UNKNOWN
Classifier: Development Status :: 3 - Alpha
Classifier: Intended Audience :: Developers
Classifier: Natural Language :: English
Classifier: License :: OSI Approved :: MIT License
Classifier: Programming Language :: Python
Classifier: Programming Language :: Python :: 2
Classifier: Programming Language :: Python :: 2.7
Classifier: Programming Language :: Python :: 3
Classifier: Programming Language :: Python :: 3.2
Classifier: Programming Language :: Python :: 3.3
Classifier: Programming Language :: Python :: 3.4
Requires-Dist: django
Requires-Dist: Pillow
